Metadata-Version: 2.1
Name: Labelme2YOLOv8
Version: 0.1.4
Summary: Labelme2YOLOv8 is a powerful tool for converting LabelMe's JSON dataset to YOLOv8  format.
Home-page: https://github.com/spatiallysaying/Labelme2YOLOv8
Author: Durga Prasad, Dhulipudi
Author-email: dgplinux@yahoo.com
Classifier: Programming Language :: Python :: 3.6
Classifier: Programming Language :: Python :: 3.7
Classifier: Programming Language :: Python :: 3.8
Classifier: Programming Language :: Python :: 3.9
